MANIFEST.in
README.rst
setup.py
niftianon/__init__.py
niftianon/anonymiser.py
niftianon/cli.py
niftianon.egg-info/PKG-INFO
niftianon.egg-info/SOURCES.txt
niftianon.egg-info/dependency_links.txt
niftianon.egg-info/entry_points.txt
niftianon.egg-info/requires.txt
niftianon.egg-info/top_level.txt
niftianon.egg-info/zip-safe