Metadata-Version: 1.0
Name: niftianon
Version: 0.1.1
Summary: Anonymiser for NIFTI images
Home-page: https://github.com/jstutters/niftianon
Author: Jon Stutters
Author-email: j.stutters@ucl.ac.uk
License: MIT
Platform: UNKNOWN
